benson/__init__.py
benson/gallery.py
benson/phil.py
benson/transformers.py
benson/imputation/__init__.py
benson/imputation/config.py
benson/imputation/distribution.py
benson/magic/__init__.py
benson/magic/base.py
benson/magic/config.py
benson/magic/ect.py
benson-0.1.5.dist-info/licenses/LICENSE
benson-0.1.5.dist-info/METADATA
benson-0.1.5.dist-info/WHEEL
benson-0.1.5.dist-info/top_level.txt
benson-0.1.5.dist-info/RECORD
