Metadata-Version: 2.4
Name: benson
Version: 0.1.5
Summary: A multiverse data cleaning tool for agent pickup.
Author-email: Krv Labs <team@krv.ai>
Requires-Python: >=3.10
License-File: LICENSE
Requires-Dist: dect
Requires-Dist: pandas>=2.2.3
Requires-Dist: pydantic>=2.10.6
Requires-Dist: scikit-learn>=1.6.1
Requires-Dist: scipy>=1.15.2
Requires-Dist: torch>=2.6.0
Dynamic: license-file
